epw/__init__.py
epw/core.py
epw/weather.py
epw-1.2.dev2.dist-info/AUTHORS
epw-1.2.dev2.dist-info/LICENSE
epw-1.2.dev2.dist-info/METADATA
epw-1.2.dev2.dist-info/WHEEL
epw-1.2.dev2.dist-info/top_level.txt
epw-1.2.dev2.dist-info/RECORD
